./.env
./.gitignore
./.python-version
./LICENSE
./PKG-INFO
./README.md
./__init__.py
./crypto_utils.py
./keystore.json
./kms_utils.py
./pyproject.toml
./server.py
./test_keystore.json
./uv.lock
./.idea/.gitignore
./.idea/mcp-cryptokit.iml
./.idea/misc.xml
./.idea/modules.xml
./.idea/vcs.xml
./.idea/workspace.xml
./.roo/mcp.json
./.vscode/launch.json
./doc/chat1.png
./doc/chat2.png
./doc/chat3.png
./doc/roocode.png
./test/keystore.json
./test/test_calltools.py
./test/test_crypto.py
mcp_cryptokit-0.1.2.dist-info/METADATA
mcp_cryptokit-0.1.2.dist-info/WHEEL
mcp_cryptokit-0.1.2.dist-info/entry_points.txt
mcp_cryptokit-0.1.2.dist-info/licenses/LICENSE
mcp_cryptokit-0.1.2.dist-info/RECORD
