Metadata-Version: 2.4
Name: mcp-cryptokit
Version: 0.1.2
Summary: A MCP server project to handle cryptographic operations.
License-File: LICENSE
Requires-Python: >=3.11
Requires-Dist: asyncio>=3.0.0
Requires-Dist: cffi>=1.16.0
Requires-Dist: cryptography>=41.0.2
Requires-Dist: gmalg>=1.0.6
Requires-Dist: gmssl>=2.5.4
Requires-Dist: httpx>=0.28.1
Requires-Dist: mcp[cli]>=1.6.0
Requires-Dist: pydantic>=2.0.0
